veriteos/__init__.py
veriteos/client.py
veriteos/counter.py
veriteos/utils.py
veriteos/validation.py
veriteos-0.1.6.dist-info/LICENSE.md
veriteos-0.1.6.dist-info/METADATA
veriteos-0.1.6.dist-info/WHEEL
veriteos-0.1.6.dist-info/top_level.txt
veriteos-0.1.6.dist-info/RECORD
